LICENSE
MANIFEST.in
README.md
setup.py
requestz/__init__.py
requestz/exceptions.py
requestz/request.py
requestz/response.py
requestz/runner.py
requestz/session.py
requestz/structure.py
requestz/utils.py
requestz.egg-info/PKG-INFO
requestz.egg-info/SOURCES.txt
requestz.egg-info/dependency_links.txt
requestz.egg-info/requires.txt
requestz.egg-info/top_level.txt
requestz.egg-info/zip-safe